.gitignore
CHANGELOG.md
LICENSE.txt
MANIFEST.in
README.md
pyproject.toml
requirements.txt
setup.py
madblog/__init__.py
madblog/__main__.py
madblog/_sorters.py
madblog/app.py
madblog/cli.py
madblog/config.py
madblog/latex.py
madblog/routes.py
madblog/uwsgi.py
madblog.egg-info/PKG-INFO
madblog.egg-info/SOURCES.txt
madblog.egg-info/dependency_links.txt
madblog.egg-info/entry_points.txt
madblog.egg-info/requires.txt
madblog.egg-info/top_level.txt
madblog/static/css/blog.css
madblog/static/css/code.css
madblog/static/css/common.css
madblog/static/css/home.css
madblog/static/fonts/Lora-Bold.eot
madblog/static/fonts/Lora-Bold.ttf
madblog/static/fonts/Lora-Bold.woff
madblog/static/fonts/Lora-Bold.woff2
madblog/static/fonts/Lora-Italic.eot
madblog/static/fonts/Lora-Italic.ttf
madblog/static/fonts/Lora-Italic.woff
madblog/static/fonts/Lora-Italic.woff2
madblog/static/fonts/Lora-Regular.eot
madblog/static/fonts/Lora-Regular.ttf
madblog/static/fonts/Lora-Regular.woff
madblog/static/fonts/Lora-Regular.woff2
madblog/static/fonts/Poppins.ttf
madblog/static/fonts/fira-sans-200.ttf
madblog/static/fonts/fira-sans-300.ttf
madblog/static/fonts/fira-sans.css
madblog/static/fonts/lora.css
madblog/static/fonts/poppins.css
madblog/static/img/favicon.ico
madblog/static/img/icon-144.png
madblog/static/img/icon-168.png
madblog/static/img/icon-192.png
madblog/static/img/icon-256.png
madblog/static/img/icon-48.png
madblog/static/img/icon-512.png
madblog/static/img/icon-72.png
madblog/static/img/icon-96.png
madblog/static/img/icon.png
madblog/static/img/rss.png
madblog/static/js/pwabuilder-sw-register.js
madblog/static/js/pwabuilder-sw.js
madblog/templates/article.html
madblog/templates/common-head.html
madblog/templates/common-tail.html
madblog/templates/footer.html
madblog/templates/index.html