Metadata-Version: 2.4
Name: madblog
Version: 0.2.39
Summary: A general-purpose framework for automation
Home-page: https://git.platypush.tech/blacklight/madblog
Author: Fabio Manganiello
Author-email: Fabio Manganiello <fabio@manganiello.tech>
License: MIT
Keywords: blog,markdown
Classifier: Topic :: Utilities
Classifier: License :: OSI Approved :: MIT License
Classifier: Development Status :: 4 - Beta
Requires-Python: >= 3.8
License-File: LICENSE.txt
Requires-Dist: flask
Requires-Dist: markdown
Requires-Dist: pygments
Requires-Dist: pyyaml
Dynamic: author
Dynamic: home-page
Dynamic: license
Dynamic: license-file
Dynamic: requires-python
